my_sdk/__init__.py
my_sdk/api.py
my_sdk/database.py
test_sdk_jaylen-1.0.0.dist-info/LICENSE
test_sdk_jaylen-1.0.0.dist-info/METADATA
test_sdk_jaylen-1.0.0.dist-info/WHEEL
test_sdk_jaylen-1.0.0.dist-info/top_level.txt
test_sdk_jaylen-1.0.0.dist-info/RECORD
