Metadata-Version: 2.1
Name: test_sdk_jaylen
Version: 1.0.0
Summary: A SDK for interacting with your API service
Home-page: https://github.com/JaylenCoder/test_sdk_jaylen
Author: JaylenCoder
Author-email: 932393678@qq.com
License: MIT
Keywords: sdk api flask mysql
Classifier: Development Status :: 3 - Alpha
Classifier: Intended Audience :: Developers
Classifier: License :: OSI Approved :: MIT License
Classifier: Programming Language :: Python :: 3
Classifier: Programming Language :: Python :: 3.6
Classifier: Programming Language :: Python :: 3.7
Classifier: Programming Language :: Python :: 3.8
Classifier: Programming Language :: Python :: 3.9
Classifier: Programming Language :: Python :: 3.10
Requires-Python: >=3.6
License-File: LICENSE
Requires-Dist: Flask
Requires-Dist: mysql-connector-python
Requires-Dist: nltk
